semantic_space/__init__.py
semantic_space/models/__init__.py
semantic_space/models/embeddings.py
semantic_space/models/grams.py
semantic_space/tools/__init__.py
semantic_space/tools/preprocessing.py
semantic_space/tools/tokens.py
semantic_space/utils/__init__.py
semantic_space/utils/exceptions.py
semantic_space/utils/log.py
semantic_space/utils/types.py
semantic_space-0.1.4.dist-info/LICENSE.txt
semantic_space-0.1.4.dist-info/METADATA
semantic_space-0.1.4.dist-info/WHEEL
semantic_space-0.1.4.dist-info/RECORD
