Metadata-Version: 2.1
Name: semantic-space
Version: 0.1.4
Summary: A basic NLP library for modelization and tokenization.
Home-page: https://github.com/ahmeterdem1/semantic-space
License: MIT
Keywords: NLP,Natural Language Processing,library
Author: Ahmet Erdem
Author-email: ahmetblk1035@gmail.com
Requires-Python: >=3.9,<4.0
Classifier: License :: OSI Approved :: MIT License
Classifier: Programming Language :: Python :: 3
Classifier: Programming Language :: Python :: 3.9
Classifier: Programming Language :: Python :: 3.10
Classifier: Programming Language :: Python :: 3.11
Classifier: Programming Language :: Python :: 3.12
Requires-Dist: numpy (>=1.20.0,<2.0.0)
Requires-Dist: tokenizers (>=0.15.0,<0.16.0)
Project-URL: Repository, https://github.com/ahmeterdem1/semantic-space
